coin_proto-0.3.0.dist-info/METADATA
coin_proto-0.3.0.dist-info/WHEEL
coin_proto-0.3.0.dist-info/entry_points.txt
coin_proto-0.3.0.dist-info/licenses/LICENSE
coin_proto/.where_now.py.swp
coin_proto/__init__.py
coin_proto/where_now.py
coin_proto-0.3.0.dist-info/RECORD
