Metadata-Version: 2.1
Name: Coin-proto
Version: 0.3.0
Summary: This prototype is a cryptocurrency trading automation system.
Author-Email: lucas_hub12 <hyeonggyunbae@gmail.com>
License: MIT
Requires-Python: >=3.10
Requires-Dist: typer>=0.15.1
